{"currentState":{"id":14,"dateCreated":"2020-05-19T11:31:15Z","isDeleted":false,"lastUpdated":"2020-05-19T11:31:15Z","finalState":false,"display":true,"modifiedBy":"Application","reportActions":[{"id":16},{"id":15},{"id":20},{"id":21},{"id":18},{"id":19},{"id":22},{"id":17}],"name":"New","createdBy":"Application","description":"Default New State"},"stateList":{"actions":{"Under Review":[]},"states":[{"id":23,"dateCreated":"2020-05-19T11:31:15Z","isDeleted":false,"lastUpdated":"2020-05-19T11:31:15Z","finalState":false,"display":true,"modifiedBy":"Application","reportActions":[],"name":"Under Review","createdBy":"Application","description":"Default Under Review"}],"rules":{"6569":{"id":23,"dateCreated":"2020-05-19T11:31:15Z","isDeleted":false,"lastUpdated":"2020-05-19T11:31:15Z","finalState":false,"display":true,"modifiedBy":"Application","reportActions":[],"name":"Under Review","createdBy":"Application","description":"Default Under Review"}},"needApproval":{"6569":false}},"workflowJustificationList":[],"reportId":null,"actionItems":0}